grapl_common/__init__.py
grapl_common/env_helpers.py
grapl_common/grapl_logger.py
grapl_common/py.typed
grapl_common/time_utils.py
grapl_common/debugger/__init__.py
grapl_common/debugger/vsc_debugger.py
grapl_common/metrics/__init__.py
grapl_common/metrics/metric_reporter.py
grapl_common/metrics/statsd_formatter.py
grapl_common-0.0.5.dist-info/METADATA
grapl_common-0.0.5.dist-info/WHEEL
grapl_common-0.0.5.dist-info/namespace_packages.txt
grapl_common-0.0.5.dist-info/top_level.txt
grapl_common-0.0.5.dist-info/RECORD
